MyCalC/__init__.py
MyCalC-1.0.dist-info/LICENCE.txt
MyCalC-1.0.dist-info/METADATA
MyCalC-1.0.dist-info/WHEEL
MyCalC-1.0.dist-info/top_level.txt
MyCalC-1.0.dist-info/RECORD
