Metadata-Version: 2.1
Name: MyCalC
Version: 1.0
Summary: Vey basic and first try
Home-page: 
Author: Somnath Paramanik
Author-email: somnathpu06@gmail.com
License: LICENCE.txt
Platform: UNKNOWN
